LICENSE
MANIFEST.in
README.md
setup.py
sphere2cube/__init__.py
sphere2cube/blender_init.py
sphere2cube/projector.blend
sphere2cube/sphere2cube.py
sphere2cube/version.py
sphere2cube.egg-info/PKG-INFO
sphere2cube.egg-info/SOURCES.txt
sphere2cube.egg-info/dependency_links.txt
sphere2cube.egg-info/entry_points.txt
sphere2cube.egg-info/top_level.txt