Metadata-Version: 2.1
Name: sphere2cube
Version: 0.3.0
Summary: Utility to map an equirectangular (cylindrical projection; skysphere) map into 6 cube (cubemap; skybox) faces
Home-page: http://github.com/Xyene/sphere2cube
Author: Tudor Brindus
Author-email: me@tbrindus.ca
License: UNKNOWN
Platform: UNKNOWN
Classifier: Development Status :: 3 - Alpha
Classifier: Environment :: Console
Classifier: Intended Audience :: Developers
Classifier: Programming Language :: Python :: 2.7
Classifier: Programming Language :: Python :: 3
Classifier: Programming Language :: Python :: 3.5
Classifier: Programming Language :: Python :: 3.6
Classifier: Programming Language :: Python :: 3.7
Classifier: Programming Language :: Python :: 3.8
Classifier: License :: OSI Approved :: GNU Affero General Public License v3 or later (AGPLv3+)
Classifier: Operating System :: OS Independent
Classifier: Programming Language :: Python
Classifier: Topic :: Artistic Software
